client/__init__.py
client/add_contact.py
client/client_DB.py
client/client_PyQT.py
client/del_contact.py
client/main_window.py
client/main_window_conv.py
client/server_DB.py
client/start_dialog.py
client/transport.py
client/window_dialog.py
common/Python_1_test.py
common/__init__.py
common/descriptor.py
common/errors.py
common/utils.py
common/variables.py
Madengine_client_messenger-0.0.1.dist-info/METADATA
Madengine_client_messenger-0.0.1.dist-info/WHEEL
Madengine_client_messenger-0.0.1.dist-info/top_level.txt
Madengine_client_messenger-0.0.1.dist-info/RECORD
