Metadata-Version: 2.1
Name: Madengine-client-messenger
Version: 0.0.1
Summary: messendger_client
Author: MadEngine
Author-email: scorpio-84@mail.ru
Requires-Dist: PyQt6
Requires-Dist: sqlalchemy
